logbind.py
logbind-2017.11.7.dist-info/LICENSE
logbind-2017.11.7.dist-info/WHEEL
logbind-2017.11.7.dist-info/METADATA
logbind-2017.11.7.dist-info/RECORD
